x2polygons/__init__.py
x2polygons/_api.py
x2polygons/geometry.py
x2polygons/plot.py
x2polygons/polygon_distance.py
x2polygons/thematic_distance.py
x2polygons/tests/test_geometry.py
x2polygons/tests/test_polygon_distance.py
x2polygons/tests/test_thematic_distance.py
x2polygons-0.172.dist-info/LICENSE
x2polygons-0.172.dist-info/METADATA
x2polygons-0.172.dist-info/WHEEL
x2polygons-0.172.dist-info/top_level.txt
x2polygons-0.172.dist-info/RECORD
